Workbook

Sheet 选品测算
A1: 序号 | B1: 品类 | C1: 商品名称/关键词 (中/马来语) | D1: 1688/货源链接 | E1: 拿货价 (RMB) | F1: 重量 (g) | G1: 国内杂费 +头程(RMB) | H1: 预估总运费 (RMB) | I1: 买家承担运费 (RM，可改) | J1: 卖家承担运费 (RMB) | K1: 售价 (RM) | L1: 平台佣金+ 手续费(RM) | M1: 总成本 (RMB) | N1: 毛利 (RM) | O1: 毛利率 | P1: 月搜索量 (参考) | Q1: TOP20平均 评价数 | R1: TOP20均价 (RM) | S1: 价格优势 (RM) | T1: 测款建议 | U1: 状态 | V1: 备注
A2: 1 | B2: 穆斯林服饰 | C2: Tudung Bawal 印花方巾 | D2: （填1688链接） | E2: 3.5 | F2: 35 | G2: 1 | H2: =CEILING(F2/10,1)*'费率参数'!$B$5 | I2: ='费率参数'!$B$6 | J2: =MAX(H2-I2*'费率参数'!$B$2,0) | K2: 12.9 | L2: =K2*('费率参数'!$B$3+'费率参数'!$B$4) | M2: =E2+G2+J2 | N2: =K2-L2-M2/'费率参数'!$B$2 | O2: =IF(K2=0,"",N2/K2) | P2: 8000 | Q2: 320 | R2: 15.9 | S2: =R2-K2 | T2: =IF(K2=0,"待填价",IF(O2<'费率参数'!$B$9,"⚠️ 利润不足",IF(OR(K2<'费率参数'!$B$11,K2>'费率参数'!$B$12),"🔶 价格带不符",IF(Q2>'费率参数'!$B$10,"🔴 竞争激烈","✅ 推荐测款")))) | U2: 待测评 | V2: 花色更新快，多色混批
A3: 2 | B3: 穆斯林服饰 | C3: Telekung 女士祷告服（简约款） | E3: 18 | F3: 350 | G3: 2 | H3: =CEILING(F3/10,1)*'费率参数'!$B$5 | I3: ='费率参数'!$B$6 | J3: =MAX(H3-I3*'费率参数'!$B$2,0) | K3: 39.9 | L3: =K3*('费率参数'!$B$3+'费率参数'!$B$4) | M3: =E3+G3+J3 | N3: =K3-L3-M3/'费率参数'!$B$2 | O3: =IF(K3=0,"",N3/K3) | P3: 3500 | Q3: 180 | R3: 49 | S3: =R3-K3 | T3: =IF(K3=0,"待填价",IF(O3<'费率参数'!$B$9,"⚠️ 利润不足",IF(OR(K3<'费率参数'!$B$11,K3>'费率参数'!$B$12),"🔶 价格带不符",IF(Q3>'费率参数'!$B$10,"🔴 竞争激烈","✅ 推荐测款")))) | U3: 待测评 | V3: 斋月前6-8周上架
A4: 3 | B4: 家居收纳 | C4: 桌面/冰箱折叠收纳盒 | E4: 8 | F4: 220 | G4: 1.5 | H4: =CEILING(F4/10,1)*'费率参数'!$B$5 | I4: ='费率参数'!$B$6 | J4: =MAX(H4-I4*'费率参数'!$B$2,0) | K4: 19.9 | L4: =K4*('费率参数'!$B$3+'费率参数'!$B$4) | M4: =E4+G4+J4 | N4: =K4-L4-M4/'费率参数'!$B$2 | O4: =IF(K4=0,"",N4/K4) | P4: 5200 | Q4: 460 | R4: 22.9 | S4: =R4-K4 | T4: =IF(K4=0,"待填价",IF(O4<'费率参数'!$B$9,"⚠️ 利润不足",IF(OR(K4<'费率参数'!$B$11,K4>'费率参数'!$B$12),"🔶 价格带不符",IF(Q4>'费率参数'!$B$10,"🔴 竞争激烈","✅ 推荐测款")))) | U4: 待测评 | V4: 主图展示收纳前后对比
A5: 4 | B5: 家居厨房 | C5: 厨房密封罐 3 件套 | E5: 6 | F5: 300 | G5: 1.5 | H5: =CEILING(F5/10,1)*'费率参数'!$B$5 | I5: ='费率参数'!$B$6 | J5: =MAX(H5-I5*'费率参数'!$B$2,0) | K5: 18.9 | L5: =K5*('费率参数'!$B$3+'费率参数'!$B$4) | M5: =E5+G5+J5 | N5: =K5-L5-M5/'费率参数'!$B$2 | O5: =IF(K5=0,"",N5/K5) | P5: 2900 | Q5: 610 | R5: 19.9 | S5: =R5-K5 | T5: =IF(K5=0,"待填价",IF(O5<'费率参数'!$B$9,"⚠️ 利润不足",IF(OR(K5<'费率参数'!$B$11,K5>'费率参数'!$B$12),"🔶 价格带不符",IF(Q5>'费率参数'!$B$10,"🔴 竞争激烈","✅ 推荐测款")))) | U5: 待测评 | V5: 注意防碎包装
A6: 5 | B6: 3C配件 | C6: 手机壳（小米/OPPO/vivo 热门机型） | E6: 2.8 | F6: 60 | G6: 1 | H6: =CEILING(F6/10,1)*'费率参数'!$B$5 | I6: ='费率参数'!$B$6 | J6: =MAX(H6-I6*'费率参数'!$B$2,0) | K6: 9.9 | L6: =K6*('费率参数'!$B$3+'费率参数'!$B$4) | M6: =E6+G6+J6 | N6: =K6-L6-M6/'费率参数'!$B$2 | O6: =IF(K6=0,"",N6/K6) | P6: 12000 | Q6: 2200 | R6: 11.9 | S6: =R6-K6 | T6: =IF(K6=0,"待填价",IF(O6<'费率参数'!$B$9,"⚠️ 利润不足",IF(OR(K6<'费率参数'!$B$11,K6>'费率参数'!$B$12),"🔶 价格带不符",IF(Q6>'费率参数'!$B$10,"🔴 竞争激烈","✅ 推荐测款")))) | U6: 待测评 | V6: 头部评价多→红海产品，谨慎
A7: 6 | B7: 美妆工具 | C7: 美妆蛋+收纳架套装 | E7: 3.2 | F7: 40 | G7: 1 | H7: =CEILING(F7/10,1)*'费率参数'!$B$5 | I7: ='费率参数'!$B$6 | J7: =MAX(H7-I7*'费率参数'!$B$2,0) | K7: 12.9 | L7: =K7*('费率参数'!$B$3+'费率参数'!$B$4) | M7: =E7+G7+J7 | N7: =K7-L7-M7/'费率参数'!$B$2 | O7: =IF(K7=0,"",N7/K7) | P7: 4400 | Q7: 350 | R7: 14.9 | S7: =R7-K7 | T7: =IF(K7=0,"待填价",IF(O7<'费率参数'!$B$9,"⚠️ 利润不足",IF(OR(K7<'费率参数'!$B$11,K7>'费率参数'!$B$12),"🔶 价格带不符",IF(Q7>'费率参数'!$B$10,"🔴 竞争激烈","✅ 推荐测款")))) | U7: 待测评 | V7: 避开化妆品成品，只做工具
A8: 7 | B8: 母婴小件 | C8: 婴儿硅胶辅食餐具 | E8: 5 | F8: 150 | G8: 1.2 | H8: =CEILING(F8/10,1)*'费率参数'!$B$5 | I8: ='费率参数'!$B$6 | J8: =MAX(H8-I8*'费率参数'!$B$2,0) | K8: 16.9 | L8: =K8*('费率参数'!$B$3+'费率参数'!$B$4) | M8: =E8+G8+J8 | N8: =K8-L8-M8/'费率参数'!$B$2 | O8: =IF(K8=0,"",N8/K8) | P8: 2100 | Q8: 270 | R8: 21.5 | S8: =R8-K8 | T8: =IF(K8=0,"待填价",IF(O8<'费率参数'!$B$9,"⚠️ 利润不足",IF(OR(K8<'费率参数'!$B$11,K8>'费率参数'!$B$12),"🔶 价格带不符",IF(Q8>'费率参数'!$B$10,"🔴 竞争激烈","✅ 推荐测款")))) | U8: 待测评 | V8: 认准食品级硅胶资质
A9: 8 | B9: 女性配饰 | C9: ins 风耳环/发饰多件套装 | E9: 2.5 | F9: 20 | G9: 0.8 | H9: =CEILING(F9/10,1)*'费率参数'!$B$5 | I9: ='费率参数'!$B$6 | J9: =MAX(H9-I9*'费率参数'!$B$2,0) | K9: 9.9 | L9: =K9*('费率参数'!$B$3+'费率参数'!$B$4) | M9: =E9+G9+J9 | N9: =K9-L9-M9/'费率参数'!$B$2 | O9: =IF(K9=0,"",N9/K9) | P9: 6800 | Q9: 410 | R9: 12.9 | S9: =R9-K9 | T9: =IF(K9=0,"待填价",IF(O9<'费率参数'!$B$9,"⚠️ 利润不足",IF(OR(K9<'费率参数'!$B$11,K9>'费率参数'!$B$12),"🔶 价格带不符",IF(Q9>'费率参数'!$B$10,"🔴 竞争激烈","✅ 推荐测款")))) | U9: 待测评 | V9: 轻小件运费优势大，适合凑单
A10: =IF(C10="","",ROW()-1) | H10: =IF(F10="","",CEILING(F10/10,1)*'费率参数'!$B$5) | I10: =IF(F10="","",'费率参数'!$B$6) | J10: =IF(F10="","",MAX(H10-I10*'费率参数'!$B$2,0)) | L10: =IF(K10="","",K10*('费率参数'!$B$3+'费率参数'!$B$4)) | M10: =IF(E10="","",E10+N(G10)+J10) | N10: =IF(OR(K10="",E10=""),"",K10-L10-M10/'费率参数'!$B$2) | O10: =IF(OR(K10="",K10=0),"",N10/K10) | S10: =IF(OR(R10="",K10=""),"",R10-K10) | T10: =IF(C10="","",IF(K10="","待填价",IF(O10<'费率参数'!$B$9,"⚠️ 利润不足",IF(OR(K10<'费率参数'!$B$11,K10>'费率参数'!$B$12),"🔶 价格带不符",IF(N(Q10)>'费率参数'!$B$10,"🔴 竞争激烈","✅ 推荐测款")))))
A11: =IF(C11="","",ROW()-1) | H11: =IF(F11="","",CEILING(F11/10,1)*'费率参数'!$B$5) | I11: =IF(F11="","",'费率参数'!$B$6) | J11: =IF(F11="","",MAX(H11-I11*'费率参数'!$B$2,0)) | L11: =IF(K11="","",K11*('费率参数'!$B$3+'费率参数'!$B$4)) | M11: =IF(E11="","",E11+N(G11)+J11) | N11: =IF(OR(K11="",E11=""),"",K11-L11-M11/'费率参数'!$B$2) | O11: =IF(OR(K11="",K11=0),"",N11/K11) | S11: =IF(OR(R11="",K11=""),"",R11-K11) | T11: =IF(C11="","",IF(K11="","待填价",IF(O11<'费率参数'!$B$9,"⚠️ 利润不足",IF(OR(K11<'费率参数'!$B$11,K11>'费率参数'!$B$12),"🔶 价格带不符",IF(N(Q11)>'费率参数'!$B$10,"🔴 竞争激烈","✅ 推荐测款")))))
A12: =IF(C12="","",ROW()-1) | H12: =IF(F12="","",CEILING(F12/10,1)*'费率参数'!$B$5) | I12: =IF(F12="","",'费率参数'!$B$6) | J12: =IF(F12="","",MAX(H12-I12*'费率参数'!$B$2,0)) | L12: =IF(K12="","",K12*('费率参数'!$B$3+'费率参数'!$B$4)) | M12: =IF(E12="","",E12+N(G12)+J12) | N12: =IF(OR(K12="",E12=""),"",K12-L12-M12/'费率参数'!$B$2) | O12: =IF(OR(K12="",K12=0),"",N12/K12) | S12: =IF(OR(R12="",K12=""),"",R12-K12) | T12: =IF(C12="","",IF(K12="","待填价",IF(O12<'费率参数'!$B$9,"⚠️ 利润不足",IF(OR(K12<'费率参数'!$B$11,K12>'费率参数'!$B$12),"🔶 价格带不符",IF(N(Q12)>'费率参数'!$B$10,"🔴 竞争激烈","✅ 推荐测款")))))
A13: =IF(C13="","",ROW()-1) | H13: =IF(F13="","",CEILING(F13/10,1)*'费率参数'!$B$5) | I13: =IF(F13="","",'费率参数'!$B$6) | J13: =IF(F13="","",MAX(H13-I13*'费率参数'!$B$2,0)) | L13: =IF(K13="","",K13*('费率参数'!$B$3+'费率参数'!$B$4)) | M13: =IF(E13="","",E13+N(G13)+J13) | N13: =IF(OR(K13="",E13=""),"",K13-L13-M13/'费率参数'!$B$2) | O13: =IF(OR(K13="",K13=0),"",N13/K13) | S13: =IF(OR(R13="",K13=""),"",R13-K13) | T13: =IF(C13="","",IF(K13="","待填价",IF(O13<'费率参数'!$B$9,"⚠️ 利润不足",IF(OR(K13<'费率参数'!$B$11,K13>'费率参数'!$B$12),"🔶 价格带不符",IF(N(Q13)>'费率参数'!$B$10,"🔴 竞争激烈","✅ 推荐测款")))))
A14: =IF(C14="","",ROW()-1) | H14: =IF(F14="","",CEILING(F14/10,1)*'费率参数'!$B$5) | I14: =IF(F14="","",'费率参数'!$B$6) | J14: =IF(F14="","",MAX(H14-I14*'费率参数'!$B$2,0)) | L14: =IF(K14="","",K14*('费率参数'!$B$3+'费率参数'!$B$4)) | M14: =IF(E14="","",E14+N(G14)+J14) | N14: =IF(OR(K14="",E14=""),"",K14-L14-M14/'费率参数'!$B$2) | O14: =IF(OR(K14="",K14=0),"",N14/K14) | S14: =IF(OR(R14="",K14=""),"",R14-K14) | T14: =IF(C14="","",IF(K14="","待填价",IF(O14<'费率参数'!$B$9,"⚠️ 利润不足",IF(OR(K14<'费率参数'!$B$11,K14>'费率参数'!$B$12),"🔶 价格带不符",IF(N(Q14)>'费率参数'!$B$10,"🔴 竞争激烈","✅ 推荐测款")))))
A15: =IF(C15="","",ROW()-1) | H15: =IF(F15="","",CEILING(F15/10,1)*'费率参数'!$B$5) | I15: =IF(F15="","",'费率参数'!$B$6) | J15: =IF(F15="","",MAX(H15-I15*'费率参数'!$B$2,0)) | L15: =IF(K15="","",K15*('费率参数'!$B$3+'费率参数'!$B$4)) | M15: =IF(E15="","",E15+N(G15)+J15) | N15: =IF(OR(K15="",E15=""),"",K15-L15-M15/'费率参数'!$B$2) | O15: =IF(OR(K15="",K15=0),"",N15/K15) | S15: =IF(OR(R15="",K15=""),"",R15-K15) | T15: =IF(C15="","",IF(K15="","待填价",IF(O15<'费率参数'!$B$9,"⚠️ 利润不足",IF(OR(K15<'费率参数'!$B$11,K15>'费率参数'!$B$12),"🔶 价格带不符",IF(N(Q15)>'费率参数'!$B$10,"🔴 竞争激烈","✅ 推荐测款")))))
A16: =IF(C16="","",ROW()-1) | H16: =IF(F16="","",CEILING(F16/10,1)*'费率参数'!$B$5) | I16: =IF(F16="","",'费率参数'!$B$6) | J16: =IF(F16="","",MAX(H16-I16*'费率参数'!$B$2,0)) | L16: =IF(K16="","",K16*('费率参数'!$B$3+'费率参数'!$B$4)) | M16: =IF(E16="","",E16+N(G16)+J16) | N16: =IF(OR(K16="",E16=""),"",K16-L16-M16/'费率参数'!$B$2) | O16: =IF(OR(K16="",K16=0),"",N16/K16) | S16: =IF(OR(R16="",K16=""),"",R16-K16) | T16: =IF(C16="","",IF(K16="","待填价",IF(O16<'费率参数'!$B$9,"⚠️ 利润不足",IF(OR(K16<'费率参数'!$B$11,K16>'费率参数'!$B$12),"🔶 价格带不符",IF(N(Q16)>'费率参数'!$B$10,"🔴 竞争激烈","✅ 推荐测款")))))
A17: =IF(C17="","",ROW()-1) | H17: =IF(F17="","",CEILING(F17/10,1)*'费率参数'!$B$5) | I17: =IF(F17="","",'费率参数'!$B$6) | J17: =IF(F17="","",MAX(H17-I17*'费率参数'!$B$2,0)) | L17: =IF(K17="","",K17*('费率参数'!$B$3+'费率参数'!$B$4)) | M17: =IF(E17="","",E17+N(G17)+J17) | N17: =IF(OR(K17="",E17=""),"",K17-L17-M17/'费率参数'!$B$2) | O17: =IF(OR(K17="",K17=0),"",N17/K17) | S17: =IF(OR(R17="",K17=""),"",R17-K17) | T17: =IF(C17="","",IF(K17="","待填价",IF(O17<'费率参数'!$B$9,"⚠️ 利润不足",IF(OR(K17<'费率参数'!$B$11,K17>'费率参数'!$B$12),"🔶 价格带不符",IF(N(Q17)>'费率参数'!$B$10,"🔴 竞争激烈","✅ 推荐测款")))))
A18: =IF(C18="","",ROW()-1) | H18: =IF(F18="","",CEILING(F18/10,1)*'费率参数'!$B$5) | I18: =IF(F18="","",'费率参数'!$B$6) | J18: =IF(F18="","",MAX(H18-I18*'费率参数'!$B$2,0)) | L18: =IF(K18="","",K18*('费率参数'!$B$3+'费率参数'!$B$4)) | M18: =IF(E18="","",E18+N(G18)+J18) | N18: =IF(OR(K18="",E18=""),"",K18-L18-M18/'费率参数'!$B$2) | O18: =IF(OR(K18="",K18=0),"",N18/K18) | S18: =IF(OR(R18="",K18=""),"",R18-K18) | T18: =IF(C18="","",IF(K18="","待填价",IF(O18<'费率参数'!$B$9,"⚠️ 利润不足",IF(OR(K18<'费率参数'!$B$11,K18>'费率参数'!$B$12),"🔶 价格带不符",IF(N(Q18)>'费率参数'!$B$10,"🔴 竞争激烈","✅ 推荐测款")))))
A19: =IF(C19="","",ROW()-1) | H19: =IF(F19="","",CEILING(F19/10,1)*'费率参数'!$B$5) | I19: =IF(F19="","",'费率参数'!$B$6) | J19: =IF(F19="","",MAX(H19-I19*'费率参数'!$B$2,0)) | L19: =IF(K19="","",K19*('费率参数'!$B$3+'费率参数'!$B$4)) | M19: =IF(E19="","",E19+N(G19)+J19) | N19: =IF(OR(K19="",E19=""),"",K19-L19-M19/'费率参数'!$B$2) | O19: =IF(OR(K19="",K19=0),"",N19/K19) | S19: =IF(OR(R19="",K19=""),"",R19-K19) | T19: =IF(C19="","",IF(K19="","待填价",IF(O19<'费率参数'!$B$9,"⚠️ 利润不足",IF(OR(K19<'费率参数'!$B$11,K19>'费率参数'!$B$12),"🔶 价格带不符",IF(N(Q19)>'费率参数'!$B$10,"🔴 竞争激烈","✅ 推荐测款")))))
A20: =IF(C20="","",ROW()-1) | H20: =IF(F20="","",CEILING(F20/10,1)*'费率参数'!$B$5) | I20: =IF(F20="","",'费率参数'!$B$6) | J20: =IF(F20="","",MAX(H20-I20*'费率参数'!$B$2,0)) | L20: =IF(K20="","",K20*('费率参数'!$B$3+'费率参数'!$B$4)) | M20: =IF(E20="","",E20+N(G20)+J20) | N20: =IF(OR(K20="",E20=""),"",K20-L20-M20/'费率参数'!$B$2) | O20: =IF(OR(K20="",K20=0),"",N20/K20) | S20: =IF(OR(R20="",K20=""),"",R20-K20) | T20: =IF(C20="","",IF(K20="","待填价",IF(O20<'费率参数'!$B$9,"⚠️ 利润不足",IF(OR(K20<'费率参数'!$B$11,K20>'费率参数'!$B$12),"🔶 价格带不符",IF(N(Q20)>'费率参数'!$B$10,"🔴 竞争激烈","✅ 推荐测款")))))
A21: =IF(C21="","",ROW()-1) | H21: =IF(F21="","",CEILING(F21/10,1)*'费率参数'!$B$5) | I21: =IF(F21="","",'费率参数'!$B$6) | J21: =IF(F21="","",MAX(H21-I21*'费率参数'!$B$2,0)) | L21: =IF(K21="","",K21*('费率参数'!$B$3+'费率参数'!$B$4)) | M21: =IF(E21="","",E21+N(G21)+J21) | N21: =IF(OR(K21="",E21=""),"",K21-L21-M21/'费率参数'!$B$2) | O21: =IF(OR(K21="",K21=0),"",N21/K21) | S21: =IF(OR(R21="",K21=""),"",R21-K21) | T21: =IF(C21="","",IF(K21="","待填价",IF(O21<'费率参数'!$B$9,"⚠️ 利润不足",IF(OR(K21<'费率参数'!$B$11,K21>'费率参数'!$B$12),"🔶 价格带不符",IF(N(Q21)>'费率参数'!$B$10,"🔴 竞争激烈","✅ 推荐测款")))))
... A60: =IF(C60="","",ROW()-1) | H60: =IF(F60="","",CEILING(F60/10,1)*'费率参数'!$B$5) | I60: =IF(F60="","",'费率参数'!$B$6) | J60: =IF(F60="","",MAX(H60-I60*'费率参数'!$B$2,0)) | L60: =IF(K60="","",K60*('费率参数'!$B$3+'费率参数'!$B$4)) | M60: =IF(E60="","",E60+N(G60)+J60) | N60: =IF(OR(K60="",E60=""),"",K60-L60-M60/'费率参数'!$B$2) | O60: =IF(OR(K60="",K60=0),"",N60/K60) | S60: =IF(OR(R60="",K60=""),"",R60-K60) | T60: =IF(C60="","",IF(K60="","待填价",IF(O60<'费率参数'!$B$9,"⚠️ 利润不足",IF(OR(K60<'费率参数'!$B$11,K60>'费率参数'!$B$12),"🔶 价格带不符",IF(N(Q60)>'费率参数'!$B$10,"🔴 竞争激烈","✅ 推荐测款")))))

Sheet 费率参数
A1: 参数 | B1: 数值 | C1: 说明（请按 Shopee 卖家学习中心最新规则修改）
A2: 汇率（1 RM = ? RMB） | B2: 1.65 | C2: 2025 年大致区间 1.60–1.72，下单结汇时以实时汇率为准
A3: 佣金率 | B3: 0.04 | C3: 普通跨境卖家通常约 4%；新店免佣期可改为 0；商城/不同类目有差异
A4: 交易手续费率 | B4: 0.0212 | C4: 约 2%（含 SST 后约 2.12%），以后台账单实际比例为准
A5: SLS 运费（每 10g，RMB） | B5: 0.25 | C5: 简化估算值！实际按 SLS 马来价卡分区/分段计费，务必以后台价卡为准
A6: 买家承担运费（RM） | B6: 6 | C6: 即藏价/买家付运费部分，实际取决于重量段与包邮活动，可逐单在 I 列覆盖
A7: 国内杂费+头程/单（RMB） | B7: 1 | C7: 取货、打包、贴面单、送仓等分摊，已在 G 列逐行填写时此行仅作参考
A8: 目标毛利率门槛 | B8: 0.3 | C8: 低于此值标红/提示利润不足
A9: 竞品评价数门槛 | B9: 500 | C9: 前排商品评价数低于此值说明头部未垄断，更适合切入
A10: 建议售价下限（RM） | B10: 9 | C10: 低于此价扣完运费佣金后利润太薄，除非纯引流款
A11: 建议售价上限（RM） | B11: 60 | C11: 新手无评价，高于此价转化困难

Sheet 使用说明
A1: Shopee 马来西亚站 · 新手选品测算表 — 使用说明
A3: 1. 你只需填白色列：B品类、C商品名、D链接、E拿货价、F重量(g)、G国内杂费、I买家承担运费（默认自动带出）、
A4: K售价(RM)、P月搜索量、Q TOP20平均评价数、R TOP20均价、U状态、V备注。灰色列为自动计算，勿手动改。
A5: 2. 所有费率集中在【费率参数】表：汇率、佣金率、交易手续费率、SLS 每 10g 运费、买家承担运费等，
A6: 规则变动时只改参数表，全表自动重算。SLS 运费为简化估算，正式定价务必对照卖家后台最新价卡。
A7: 3. 核心公式：
A8: 预估总运费 = CEILING(重量/10g) × 每10g费率
A9: 卖家承担运费 = MAX(总运费 − 买家承担运费×汇率, 0)（即“藏价”成本）
A10: 总成本(RMB) = 拿货价 + 国内杂费/头程 + 卖家承担运费
A11: 毛利(RM) = 售价 − 售价×(佣金率+手续费率) − 总成本÷汇率
A12: 4. 测款建议判定逻辑：毛利率<30% → 利润不足；售价不在 RM9–60 → 价格带不符；
A13: TOP20 平均评价数>500 → 竞争激烈；全部通过 → ✅ 推荐测款。门槛均可在参数表调整。
... A21: 9.9/10.10/11.11/12.12 提前 2–3 周备货；年底雨季备雨伞雨衣防水鞋套。
